spint/__init__.py
spint/count_model.py
spint/dispersion.py
spint/gravity.py
spint/utils.py
spint/vec_SA.py
spint/tests/__init__.py
spint/tests/test_count_model.py
spint/tests/test_dispersion.py
spint/tests/test_gravity.py
spint/tests/test_vec_SA.py
spint-1.0.6.dist-info/LICENSE
spint-1.0.6.dist-info/METADATA
spint-1.0.6.dist-info/WHEEL
spint-1.0.6.dist-info/top_level.txt
spint-1.0.6.dist-info/RECORD
